torchsummary/__init__.py
torchsummary/formatting.py
torchsummary/layer_info.py
torchsummary/model_statistics.py
torchsummary/torchsummary.py
torch_summary-1.4.5.dist-info/LICENSE
torch_summary-1.4.5.dist-info/METADATA
torch_summary-1.4.5.dist-info/WHEEL
torch_summary-1.4.5.dist-info/top_level.txt
torch_summary-1.4.5.dist-info/RECORD
