Metadata-Version: 2.1
Name: torch-summary
Version: 1.4.5
Summary: Model summary in PyTorch, based off of the original torchsummary.
Home-page: https://github.com/tyleryep/torchinfo
Author: Tyler Yep @tyleryep
Author-email: tyep10@gmail.com
License: MIT
Keywords: torch pytorch torchsummary torch-summary summary keras deep-learning ml torchinfo torch-info visualize model statistics layer
Platform: UNKNOWN
Classifier: License :: OSI Approved :: MIT License
Classifier: Operating System :: OS Independent
Classifier: Programming Language :: Python :: 3
Classifier: Programming Language :: Python :: 3 :: Only
Classifier: Programming Language :: Python :: 3.6
Classifier: Programming Language :: Python :: 3.7
Classifier: Programming Language :: Python :: 3.8
Classifier: Programming Language :: Python :: 3.9
Requires-Python: >=3.6
